pytrains/__init__.py
pytrains/cli.py
pytrains/data.py
pytrains/rawData.py
pytrains/service.py
pytrains/station.py
pytrains/untangle.py
tests/__init__.py
tests/test_data_utilities.py
tests/test_full.py
PyTrains-0.0.7.dist-info/LICENSE
PyTrains-0.0.7.dist-info/METADATA
PyTrains-0.0.7.dist-info/WHEEL
PyTrains-0.0.7.dist-info/entry_points.txt
PyTrains-0.0.7.dist-info/top_level.txt
PyTrains-0.0.7.dist-info/RECORD
