Metadata-Version: 2.1
Name: PyTrains
Version: 0.0.7
Summary: Get realtime UK trains information through a simple Python API.
Home-page: https://github.com/w-henderson/PyTrains
Author: w-henderson
License: GPL-3.0
Project-URL: Source, https://github.com/w-henderson/PyTrains
Keywords: trains,train times,uk,cli,timetable
Platform: UNKNOWN
Classifier: License :: OSI Approved :: MIT License
Classifier: Operating System :: OS Independent
Classifier: Programming Language :: Python :: 3
Requires-Python: >=3.6
Requires-Dist: requests
Requires-Dist: colorama
Provides-Extra: tests
Requires-Dist: pytest ; extra == 'tests'
